d361api/__init__.py
d361api/api_client.py
d361api/api_response.py
d361api/configuration.py
d361api/exceptions.py
d361api/py.typed
d361api/rest.py
d361api/d361api/__init__.py
d361api/d361api/access_scope_customer_v2.py
d361api/d361api/access_scope_level.py
d361api/d361api/add_category_request.py
d361api/d361api/add_category_response.py
d361api/d361api/add_media_file_response_customer.py
d361api/d361api/add_media_folder_request_customer.py
d361api/d361api/add_reader_group_request_v2.py
d361api/d361api/add_reader_request_v2.py
d361api/d361api/add_team_account_customer.py
d361api/d361api/add_update_access_scope_customer_v2.py
d361api/d361api/add_user_data.py
d361api/d361api/add_user_data_customer_api_response.py
d361api/d361api/ai_additional_feedback_info.py
d361api/d361api/ai_assistive_search.py
d361api/d361api/ai_assistive_search_request.py
d361api/d361api/all_files_with_count_customer.py
d361api/d361api/all_files_with_count_response_customer.py
d361api/d361api/api_definition_inforamtion_customer.py
d361api/d361api/api_docs_import_data_customer.py
d361api/d361api/api_docs_resync_data_customer.py
d361api/d361api/api_documentation_import_response_customer.py
d361api/d361api/api_documentation_resync_response_customer.py
d361api/d361api/api_error_and_warnings_data.py
d361api/d361api/api_logs.py
d361api/d361api/api_reference_logs_data_customer.py
d361api/d361api/api_reference_logs_wrap_response_customer.py
d361api/d361api/api_reference_publish_request_customer.py
d361api/d361api/api_references_api.py
d361api/d361api/article_access_info.py
d361api/d361api/article_content_type.py
d361api/d361api/article_matched_data.py
d361api/d361api/article_setting_customer.py
d361api/d361api/article_setting_customer_response.py
d361api/d361api/article_simple_data_customer.py
d361api/d361api/article_simple_data_customer_response.py
d361api/d361api/article_simple_version_customer.py
d361api/d361api/article_stale_status.py
d361api/d361api/article_status_customer.py
d361api-2.2.7.dist-info/METADATA
d361api-2.2.7.dist-info/WHEEL
d361api-2.2.7.dist-info/licenses/LICENSE
d361api-2.2.7.dist-info/RECORD
