Metadata-Version: 2.4
Name: d361api
Version: 2.2.7
Summary: Document360 Customer API
Project-URL: Homepage, https://github.com/twardoch/d361api
Project-URL: Repository, https://github.com/twardoch/d361api
Project-URL: Documentation, https://apidocs.document360.io/docs
Author-email: Document360 Support <support@document360.com>
License: NoLicense
License-File: LICENSE
Keywords: Document360 Customer API,OpenAPI,OpenAPI-Generator
Classifier: Development Status :: 4 - Beta
Classifier: Intended Audience :: Developers
Classifier: Programming Language :: Python :: 3
Classifier: Programming Language :: Python :: 3.8
Classifier: Programming Language :: Python :: 3.9
Classifier: Programming Language :: Python :: 3.10
Classifier: Programming Language :: Python :: 3.11
Classifier: Programming Language :: Python :: 3.12
Requires-Python: >=3.8
Requires-Dist: aiohttp-retry>=2.8.3
Requires-Dist: aiohttp>=3.8.4
Requires-Dist: pydantic>=2
Requires-Dist: python-dateutil>=2.8.2
Requires-Dist: typing-extensions>=4.7.1
Requires-Dist: urllib3<3.0.0,>=1.25.3
Provides-Extra: dev
Requires-Dist: mypy>=1.5; extra == 'dev'
Requires-Dist: pytest-cov>=2.8.1; extra == 'dev'
Requires-Dist: pytest>=7.2.1; extra == 'dev'
Requires-Dist: ruff; extra == 'dev'
Requires-Dist: tox>=3.9.0; extra == 'dev'
Requires-Dist: types-python-dateutil>=2.8.19.14; extra == 'dev'
Provides-Extra: test
Requires-Dist: mypy>=1.5; extra == 'test'
Requires-Dist: pytest-cov>=2.8.1; extra == 'test'
Requires-Dist: pytest>=7.2.1; extra == 'test'
Requires-Dist: types-python-dateutil>=2.8.19.14; extra == 'test'
